pyannotebook/__init__.py
pyannotebook/_frontend.py
pyannotebook/_version.py
pyannotebook/annotation.py
pyannotebook/labels.py
pyannotebook/pyannotebook.py
pyannotebook/rttm.py
pyannotebook/wavesurfer.py
pyannotebook/labextension/build_log.json
pyannotebook/labextension/package.json
pyannotebook/labextension/static/lib_index_js.ab8d35434f4d6a61893d.js
pyannotebook/labextension/static/lib_index_js.ab8d35434f4d6a61893d.js.map
pyannotebook/labextension/static/lib_plugin_js.32b250c700714324183d.js
pyannotebook/labextension/static/lib_plugin_js.32b250c700714324183d.js.map
pyannotebook/labextension/static/lib_widget_js.0f6bf81b3968e7a8dc41.js
pyannotebook/labextension/static/lib_widget_js.0f6bf81b3968e7a8dc41.js.map
pyannotebook/labextension/static/lib_widget_js.1f4df3f32759f88e8c8e.js
pyannotebook/labextension/static/lib_widget_js.1f4df3f32759f88e8c8e.js.map
pyannotebook/labextension/static/lib_widget_js.2ce733f0d3928a2faeab.js
pyannotebook/labextension/static/lib_widget_js.2ce733f0d3928a2faeab.js.map
pyannotebook/labextension/static/lib_widget_js.5848b03e0c0f2e07211b.js
pyannotebook/labextension/static/lib_widget_js.5848b03e0c0f2e07211b.js.map
pyannotebook/labextension/static/lib_widget_js.5aab188af617c8480816.js
pyannotebook/labextension/static/lib_widget_js.5aab188af617c8480816.js.map
pyannotebook/labextension/static/lib_widget_js.a7363db06b8ea1e9ae73.js
pyannotebook/labextension/static/lib_widget_js.a7363db06b8ea1e9ae73.js.map
pyannotebook/labextension/static/lib_widget_js.e99d97413ad4b7624b78.js
pyannotebook/labextension/static/lib_widget_js.e99d97413ad4b7624b78.js.map
pyannotebook/labextension/static/remoteEntry.2df37589fbb3419b3bcf.js.map
pyannotebook/labextension/static/remoteEntry.50df89befe2cdf18b766.js.map
pyannotebook/labextension/static/remoteEntry.53735cedd023e50eec22.js.map
pyannotebook/labextension/static/remoteEntry.b13656d8d3c3d42ba0cb.js
pyannotebook/labextension/static/remoteEntry.b13656d8d3c3d42ba0cb.js.map
pyannotebook-0.1.0.dev0.dist-info/METADATA
pyannotebook-0.1.0.dev0.dist-info/WHEEL
pyannotebook-0.1.0.dev0.dist-info/licenses/LICENSE.txt
pyannotebook-0.1.0.dev0.dist-info/RECORD
